kafkaproducerconsumer_confluent/KafkaTopics.py
kafkaproducerconsumer_confluent/__init__.py
kafkaproducerconsumer_confluent-0.0.7.dist-info/LICENSE
kafkaproducerconsumer_confluent-0.0.7.dist-info/METADATA
kafkaproducerconsumer_confluent-0.0.7.dist-info/WHEEL
kafkaproducerconsumer_confluent-0.0.7.dist-info/top_level.txt
kafkaproducerconsumer_confluent-0.0.7.dist-info/RECORD
