Metadata-Version: 2.1
Name: kafkaproducerconsumer-confluent
Version: 0.0.7
Summary: Kafka package to retrieve or push data to a topic
Author: JathinNagesh
Author-email: jathinnagesh@outlook.com
Classifier: Programming Language :: Python :: 3
Classifier: License :: OSI Approved :: MIT License
Classifier: Operating System :: OS Independent
Requires-Python: >=3.6
License-File: LICENSE
